sfmanager/__init__.py
sfmanager/sfauth.py
sfmanager/sfmanager.py
sfmanager/tests/test_sfauth.py
sfmanager/tests/test_sfmanager.py
python_sfmanager-0.8.5.dev1.dist-info/AUTHORS
python_sfmanager-0.8.5.dev1.dist-info/LICENSE
python_sfmanager-0.8.5.dev1.dist-info/METADATA
python_sfmanager-0.8.5.dev1.dist-info/WHEEL
python_sfmanager-0.8.5.dev1.dist-info/entry_points.txt
python_sfmanager-0.8.5.dev1.dist-info/pbr.json
python_sfmanager-0.8.5.dev1.dist-info/top_level.txt
python_sfmanager-0.8.5.dev1.dist-info/RECORD
